_examples/__init__.py
examples/README.rst
examples/__init__.py
tests/__init__.py
fin_model_course-0.1.17.dist-info/LICENSE.md
fin_model_course-0.1.17.dist-info/METADATA
fin_model_course-0.1.17.dist-info/WHEEL
fin_model_course-0.1.17.dist-info/entry_points.txt
fin_model_course-0.1.17.dist-info/top_level.txt
fin_model_course-0.1.17.dist-info/RECORD
