Metadata-Version: 2.1
Name: fin-model-course
Version: 0.1.17
Summary: A Python and Excel Financial Modeling Course
Home-page: https://github.com/nickderobertis/fin-model-course
Author: Nick DeRobertis
Author-email: whoopnip@gmail.com
License: MIT
Project-URL: Code, https://github.com/nickderobertis/fin-model-course
Project-URL: Documentation, https://nickderobertis.github.io/fin-model-course
Platform: UNKNOWN
Classifier: Development Status :: 3 - Alpha
Classifier: Intended Audience :: Developers
Classifier: Programming Language :: Python :: 3.6
Classifier: Programming Language :: Python :: 3.7
